CelestPlotter/CelSphere.py
CelestPlotter/InNCon.py
CelestPlotter/__init__.py
CelestPlotter-1.0.dist-info/METADATA
CelestPlotter-1.0.dist-info/WHEEL
CelestPlotter-1.0.dist-info/top_level.txt
CelestPlotter-1.0.dist-info/RECORD
