Metadata-Version: 2.1
Name: CelestPlotter
Version: 1.0
Summary: RA and Dec Conversion and Plotter package
Home-page: UNKNOWN
Author: Aditi Das
Author-email: <aditi.das1601@gmail.com>
License: UNKNOWN
Platform: UNKNOWN
Requires-Dist: numpy
Requires-Dist: matplotlib
Requires-Dist: astropy
